beacon_dl/__init__.py
beacon_dl/auth.py
beacon_dl/browser.py
beacon_dl/config.py
beacon_dl/constants.py
beacon_dl/content.py
beacon_dl/downloader.py
beacon_dl/exceptions.py
beacon_dl/graphql.py
beacon_dl/history.py
beacon_dl/main.py
beacon_dl/models.py
beacon_dl/utils.py
beacon_dl-0.5.0.dist-info/METADATA
beacon_dl-0.5.0.dist-info/WHEEL
beacon_dl-0.5.0.dist-info/entry_points.txt
beacon_dl-0.5.0.dist-info/RECORD
