Metadata-Version: 2.4
Name: beacon-dl
Version: 0.5.0
Summary: Beacon TV Downloader - Direct HTTP downloads, no yt-dlp required
Requires-Python: >=3.10
Requires-Dist: httpx>=0.28.0
Requires-Dist: playwright>=1.56.0
Requires-Dist: pydantic-settings>=2.12.0
Requires-Dist: pydantic>=2.12.4
Requires-Dist: rich>=14.2.0
Requires-Dist: typer>=0.20.0
Provides-Extra: dev
Requires-Dist: pre-commit>=4.0.0; extra == 'dev'
Requires-Dist: pytest-cov>=6.0.0; extra == 'dev'
Requires-Dist: pytest-httpx>=0.35.0; extra == 'dev'
Requires-Dist: pytest-mock>=3.12.0; extra == 'dev'
Requires-Dist: pytest-timeout>=2.2.0; extra == 'dev'
Requires-Dist: pytest>=8.0.0; extra == 'dev'
Requires-Dist: ruff>=0.11.0; extra == 'dev'
